sphinxext/photofinish/__init__.py
sphinxext/photofinish/svgtopng.py
sphinxext_photofinish-0.1.11.dist-info/LICENSE.md
sphinxext_photofinish-0.1.11.dist-info/METADATA
sphinxext_photofinish-0.1.11.dist-info/WHEEL
sphinxext_photofinish-0.1.11.dist-info/top_level.txt
sphinxext_photofinish-0.1.11.dist-info/RECORD
