Metadata-Version: 2.1
Name: sphinxext-photofinish
Version: 0.1.11
Summary: Sphinx Extension that creates responsive images.
Home-page: https://github.com/wpilibsuite/sphinxext-photofinish
Author: WPILib
Author-email: developers@wpilib.org
Classifier: Environment :: Plugins
Classifier: Environment :: Web Environment
Classifier: Framework :: Sphinx :: Extension
Classifier: Intended Audience :: Developers
Classifier: License :: OSI Approved :: MIT License
Classifier: Natural Language :: English
Classifier: Operating System :: OS Independent
Classifier: Programming Language :: Python :: 3.8
Classifier: Programming Language :: Python :: 3.9
Classifier: Programming Language :: Python :: 3.10
Classifier: Programming Language :: Python :: 3.11
Classifier: Programming Language :: Python :: 3.12
Classifier: Programming Language :: Python
Classifier: Topic :: Documentation :: Sphinx
Classifier: Topic :: Documentation
Classifier: Topic :: Software Development :: Documentation
Classifier: Topic :: Text Processing
Classifier: Topic :: Utilities
Requires-Python: >=3.8
License-File: LICENSE.md
Requires-Dist: sphinx >=2.0
Requires-Dist: beautifulsoup4 >=4
Requires-Dist: pillow >=10.0.1
Requires-Dist: tinycss2 >=1.1.1
